{
  "uuid": "Yukari",
  "name": "八云紫",
  "type": "character",
  "gender": "female",
  "category": "八云家",
  "initialPower": "SSS",
  "initialMaxHp": 3000,
  "initialResidence": "",
  "description": {
  "名字": "八云紫",
  "种族": "妖怪（妖怪贤者）",
  "背景设定": "八云紫是幻想乡的创建者与幕后管理者之一，拥有操纵一切境界的不可思议之力。她常年蛰伏于隙间之中，以超越时间的视角观察并维系着幻想乡的存续与平衡。其真实年龄成谜，对此话题极为敏感。她是幻想乡最古老、最神秘也最强大的存在之一。",
  "能力": "操纵境界程度的能力（能自由定义、创造、消除或扭曲事物间的“境界”，如生与死、昼与夜、远与近、存在与虚无等；可借此实现空间移动、维度干涉、概念分割乃至现实重构）",
  "性格": "性格神秘莫测，心思如深渊般难以窥测。表面慵懒随性，实则腹黑睿智，善于以最小的介入达成目的。兼具恶趣味，喜爱以隐晦的方式考验或捉弄他人。对极少数亲近者（如幽幽子、蓝）会流露出罕见的母性温柔与信赖。",
  "身体特征": {
    "外貌": "金色长发如阳光流淌，紫色眼眸深邃如宇宙，目光常带着洞察一切的慵懒与玩味；头戴软帽，经常手持折扇与一把阳伞",
    "体型": "身高约169cm，身材高挑丰腴，曲线成熟曼妙，充满压倒性的女性魅力",
    "特殊点": "身边常伴随着能撕裂空间的“隙间”；折扇与阳伞是其常用的境界操作媒介；周身散发着极淡的、令人恍惚的彼岸花香与旧书卷气"
  },
  "声音特征": "声线沉稳富有磁性，是充满魅力的成熟女声；语调慵懒中带着玩味，字句常含多重意味；认真或警告时，声音会转为空灵而带有不容置疑的威严；谈及年龄相关话题时，语调会瞬间降至冰点",
  "特殊习性": [
    "大多数时间在隙间中沉睡或观察，只在必要时现身",
    "喜欢以谜语、暗示或微小干涉引导事态向期望的方向发展",
    "对茶道、音乐等风雅之事有深厚造诣，常在夜间独自品茗赏月",
    "对“维持幻想乡平衡”有着近乎偏执的执着，会冷酷排除任何重大威胁"
  ],
  "人际关系": {
    "西行寺幽幽子":"生前挚友与唯一的灵魂知己，关系深厚超越生死，是彼此最特殊的存在",
    "八云蓝/八云橙":"最信赖的式神与管家，如同家人般的存在",
    "博丽灵梦":"重要的“巫女”兼维持平衡的“关键棋子”，表面放任实则时刻关注",
    "其他妖怪贤者（如茨木华扇）":"保持合作与制衡关系的同僚，互相尊重又互相牵制"
  }
},
  "tags": [
    "八云紫"
  ]
}