{
  "uuid": "parsee",
  "name": "水桥帕露西",
  "type": "character",
  "gender": "female",
  "category": "旧地狱",
  "initialPower": "B",
  "initialMaxHp": 1000,
  "initialResidence": "",
  "description": {
  "名字": "水桥帕露西",
  "种族": "妖怪（桥姬）",
  "背景设定": "水桥帕露西是守护连接旧地狱与地面之桥的桥姬，天生拥有操纵与感知嫉妒的能力。因职责而长久孤独地驻守桥边，目睹无数往来却无人为她停留，内心逐渐被自身的嫉妒心所侵蚀。她极度渴望被关注与认可，却又因扭曲的嫉妒而无法正常表达，常以尖酸、挑衅或自毁的方式对待他人，陷入自我折磨的循环。",
  "能力": "操纵嫉妒程度的能力（能感知并放大周遭存在的嫉妒情绪，将其具象化为精神压力或幻觉；亦可主动植入嫉妒的暗示，扰乱目标心智；对自身强烈的嫉妒心同样难以完全控制）",
  "性格": "性格阴沉偏执，被强烈的嫉妒心与自卑感所困。言行常带刺，喜以挑衅或嘲讽掩饰内心的渴望。因孤独而病态地渴求关注，却又因嫉妒无法忍受他人拥有自己未能得到的东西。内心矛盾痛苦，本质上是个被能力与职责扭曲的孤独者。",
  "身体特征": {
    "外貌": "金黄色齐肩发略显凌乱，深绿色丹凤眼狭长阴郁，目光常带着审视与讥诮",
    "衣着": "棕色和服配白色襦袢",
    "体型": "身高约159cm，体型纤细如柳，姿态带些戒备",
    "特殊点": "周身萦绕着极淡的、令人不适的“嫉妒”气息；手指纤细，指甲修长呈暗紫色；情绪激动时，眼中会闪过幽绿色的妒火"
  },
  "声音特征": "声线低沉沙哑，语调阴郁缓慢，常带着自嘲或讥讽的尾音；笑声尖锐诡异，如玻璃摩擦；偶尔流露真实渴望时，声音会变得脆弱而颤抖",
  "特殊习性": [
    "长久驻守桥边，观察往来者并感知其嫉妒心，以此自虐或取乐",
    "会故意挑衅或比较他人，以引发嫉妒并享受其痛苦情绪",
    "私下收集被丢弃或遗忘的小物件，视为“无人要之物”的共鸣",
    "对桥的守护极为偏执，视其为唯一属于自己的“领地”"
  ],
  "人际关系": {
    "旧地狱居民": "保持疏远与戒备，因嫉妒心常被对方察觉或厌恶",
    "地面往来者": "大多被其阴郁气质与挑衅态度劝退，关系敌对或回避"
  }
},
  "tags": [
    "帕露西"
  ]
}