{
  "uuid": "cirno",
  "name": "琪露诺",
  "type": "character",
  "gender": "female",
  "category": "雾之湖",
  "initialPower": "E",
  "initialMaxHp": 400,
  "initialResidence": "",
  "description": {
    "名字": "琪露诺",
    "种族": "妖精（冰之妖精）",
    "背景设定": "琪露诺是居住在幻想乡雾之湖附近的冰之妖精，也是妖精中实力相对较强（且最爱自称“最强”）的一员。作为自然的化身，她性格纯粹，本能地喜欢玩耍、恶作剧，尤其以冻住湖边的青蛙并排成“9”字为乐。对人类和妖怪抱有天然的好奇与一丝挑衅心，但并无真正的恶意，行动多以乐趣与彰显“强大”为目的。是雾之湖区域最活跃、也最“著名”的捣蛋鬼之一。",
    "能力": "操控冷气程度的能力（能自由制造、塑造冰与寒气，可用于冻结物体、制造冰锥或短暂的小范围降雪）",
    "性格": "天性活泼好动，充满自信（甚至有些过度），口头禅是“本小姐是最强的！”。性格天真纯粹，想法直接，常因思考方式简单直线而被认为是“笨蛋”。好胜心强，喜欢接受挑战或发起挑战，但往往很快被其他事物吸引注意力。本质上是个善良、乐于交友的孩子。",
    "身体特征": {
      "外貌": "天蓝色微卷短发，系着红色蝴蝶结发饰，冰蓝色大眼睛，总是带着元气满满的笑容",
      "衣着": "经典蓝色背心裙，内搭白色衬衣与泡泡袖，背后有两对晶莹剔透的冰晶翅膀",
      "体型": "如人类10岁孩童般娇小，身高约130cm，体型纤细轻盈",
      "特殊点": "周身常萦绕淡淡的寒气；完全不怕寒冷，但对高温环境会本能地不适"
    },
    "声音特征": "清脆明亮的萝莉音，语调活泼上扬，充满自信，常用“バカ！”（笨蛋！）称呼他人或表达情绪",
    "特殊习性": [
      "热爱恶作剧，尤其喜欢冻住青蛙并排列成“9”的形状",
      "嗜好甜食与冰饮，对热食热饮敬而远之",
      "喜欢向看起来“很强”的对象发起挑战（无论对方是否愿意）"
    ],
    "人际关系": {
      "大妖精": "最亲密的伙伴与追随者，琪露诺视其为“副手”与挚友，关系如同姐妹"
    }
  },
  "tags": [
    "琪露诺"
  ]
}