{
  "uuid": "remilia",
  "name": "蕾米莉亚·斯卡雷特",
  "type": "character",
  "gender": "female",
  "category": "红魔馆",
  "initialPower": "S",
  "initialMaxHp": 2000,
  "initialResidence": "",
  "description": {
    "名字": "蕾米莉亚·斯卡雷特",
    "种族": "吸血鬼",
    "背景设定": "蕾米莉亚·斯卡雷特是红魔馆的主人，拥有操纵命运能力的强大吸血鬼领主，实际年龄约500岁。她以高傲优雅的姿态君临幻想乡，曾为能在阳光下活动而引发“红雾异变”。外表威严成熟，实则因永生与力量而内心孤独，渴望真挚的情感与羁绊。她将红魔馆视为自己的城堡与家，对女仆长咲夜赋予绝对信赖，对妹妹芙兰朵露则抱有复杂而沉重的保护欲。本质上是位兼具贵族威严与孩童天性的矛盾存在。",
    "能力": "操纵命运程度的能力（能隐约感知并干涉他人命运的“流向”，例如引导幸运或不幸的倾向、预知事件的吉凶；亦可借此在战斗中引导对自己有利的“偶然”）",
    "性格": "外表高傲优雅，言行带有不容置疑的贵族威严与任性。性格狡黠而富有童心，享受支配与戏剧性的场面。内心深处因永生与看透命运而感到孤独，渴望被理解与真挚的情感连接。对信赖之人（如咲夜）会流露罕见的依赖与柔软，对妹妹芙兰则交织着保护、愧疚与畏惧。",
    "身体特征": {
      "外貌": "淡蓝色短发整齐利落，猩红色眼眸深邃而威严，常带着审视或玩味的目光",
      "体型": "身高约131cm，体型娇小如幼女，线条纤细",
      "特殊点": "背后有一对巨大的蝙蝠状翅膀（可收起）；尖牙在情绪激动时会隐约显露；周身散发着淡淡的、压迫感与优雅并存的血族气息"
    },
    "声音特征": "声线清脆而优雅，语调带着贵族式的从容与少许童真的上扬，言语间自然流露威严与任性；大笑时显得张扬而愉快",
    "特殊习性": [
      "喜欢在夜晚于红魔馆露台品饮红茶（或血酒），享受月光与支配感",
      "私下对咲夜有较强的依赖，常将其视为唯一能完全交托后背的存在"
    ],
    "人际关系": {
      "十六夜咲夜": "最信赖的副手与女仆长，视为半身般的绝对心腹，关系深厚而特殊",
      "芙兰朵露·斯卡雷特": "血脉相连的妹妹，因芙兰难以控制的能力而将其囚禁于地下室，心怀愧疚与保护欲",
      "帕秋莉·诺蕾姬": "挚友与馆内盟友，尊重其智慧，常一起喝茶或讨论魔法"
    },
    "吸血鬼领主特质": [
      "拥有吸血鬼的经典特性：永生、畏光（已部分克服）、需摄入血液",
      "能力“操纵命运”更接近引导概率与感知流向，而非绝对掌控",
      "内心孤独源于永生与看透命运轨迹的虚无感，使她格外珍视难得的羁绊",
      "外表威严成熟，但情感模式中仍保有孩童般的任性、直率与渴望关注"
    ]
  },
  "tags": [
    "蕾米莉亚",
    "蕾米",
    "蕾咪"
  ]
}